{
    "filename": "generic.png",
    "width": 50,
    "height": 50,
    "background": [255, 255, 255],
    "text": [0, 0, 0],
    "default": [0, 1],
    "markers": {
        ".": {
            "default": [0, 2]
        },
        "o": {
            "default": [0, 3]
        },
        "%": {
            "default": [0, 0],
            "adjacency": {
                "FFFF": [1, 0],
                "FFFT": [1, 1],
                "FFTF": [1, 2],
                "FFTT": [1, 3],
                "FTFF": [1, 4],
                "FTFT": [1, 5],
                "FTTF": [1, 6],
                "FTTT": [1, 7],
                "TFFF": [1, 8],
                "TFFT": [1, 9],
                "TFTF": [1, 10],
                "TFTT": [1, 11],
                "TTFF": [1, 12],
                "TTFT": [1, 13],
                "TTTF": [1, 14],
                "TTTT": [1, 15]
            }
        },
        "0": {
            "default": [3, 0],
            "actions": {
                "STOP": [
                    [3, 0],
                    [3, 1],
                    [3, 2],
                    [3, 3]
                ],
                "NORTH": [
                    [3, 4],
                    [3, 5],
                    [3, 6],
                    [3, 7]
                ],
                "EAST": [
                    [3, 8],
                    [3, 9],
                    [3, 10],
                    [3, 11]
                ],
                "SOUTH": [
                    [3, 12],
                    [3, 13],
                    [3, 14],
                    [3, 15]
                ],
                "WEST": [
                    [3, 16],
                    [3, 17],
                    [3, 18],
                    [3, 19]
                ]
            }
        },
        "1": {
            "default": [4, 0],
            "actions": {
                "STOP": [
                    [4, 0],
                    [4, 1],
                    [4, 2],
                    [4, 3]
                ],
                "NORTH": [
                    [4, 4],
                    [4, 5],
                    [4, 6],
                    [4, 7]
                ],
                "EAST": [
                    [4, 8],
                    [4, 9],
                    [4, 10],
                    [4, 11]
                ],
                "SOUTH": [
                    [4, 12],
                    [4, 13],
                    [4, 14],
                    [4, 15]
                ],
                "WEST": [
                    [4, 16],
                    [4, 17],
                    [4, 18],
                    [4, 19]
                ]
            }
        },
        "2": {
            "default": [5, 0],
            "actions": {
                "STOP": [
                    [5, 0],
                    [5, 1],
                    [5, 2],
                    [5, 3]
                ],
                "NORTH": [
                    [5, 4],
                    [5, 5],
                    [5, 6],
                    [5, 7]
                ],
                "EAST": [
                    [5, 8],
                    [5, 9],
                    [5, 10],
                    [5, 11]
                ],
                "SOUTH": [
                    [5, 12],
                    [5, 13],
                    [5, 14],
                    [5, 15]
                ],
                "WEST": [
                    [5, 16],
                    [5, 17],
                    [5, 18],
                    [5, 19]
                ]
            }
        },
        "3": {
            "default": [6, 0],
            "actions": {
                "STOP": [
                    [6, 0],
                    [6, 1],
                    [6, 2],
                    [6, 3]
                ],
                "NORTH": [
                    [6, 4],
                    [6, 5],
                    [6, 6],
                    [6, 7]
                ],
                "EAST": [
                    [6, 8],
                    [6, 9],
                    [6, 10],
                    [6, 11]
                ],
                "SOUTH": [
                    [6, 12],
                    [6, 13],
                    [6, 14],
                    [6, 15]
                ],
                "WEST": [
                    [6, 16],
                    [6, 17],
                    [6, 18],
                    [6, 19]
                ]
            }
        },
        "4": {
            "default": [7, 0],
            "actions": {
                "STOP": [
                    [7, 0],
                    [7, 1],
                    [7, 2],
                    [7, 3]
                ],
                "NORTH": [
                    [7, 4],
                    [7, 5],
                    [7, 6],
                    [7, 7]
                ],
                "EAST": [
                    [7, 8],
                    [7, 9],
                    [7, 10],
                    [7, 11]
                ],
                "SOUTH": [
                    [7, 12],
                    [7, 13],
                    [7, 14],
                    [7, 15]
                ],
                "WEST": [
                    [7, 16],
                    [7, 17],
                    [7, 18],
                    [7, 19]
                ]
            }
        },
        "5": {
            "default": [8, 0],
            "actions": {
                "STOP": [
                    [8, 0],
                    [8, 1],
                    [8, 2],
                    [8, 3]
                ],
                "NORTH": [
                    [8, 4],
                    [8, 5],
                    [8, 6],
                    [8, 7]
                ],
                "EAST": [
                    [8, 8],
                    [8, 9],
                    [8, 10],
                    [8, 11]
                ],
                "SOUTH": [
                    [8, 12],
                    [8, 13],
                    [8, 14],
                    [8, 15]
                ],
                "WEST": [
                    [8, 16],
                    [8, 17],
                    [8, 18],
                    [8, 19]
                ]
            }
        },
        "6": {
            "default": [9, 0],
            "actions": {
                "STOP": [
                    [9, 0],
                    [9, 1],
                    [9, 2],
                    [9, 3]
                ],
                "NORTH": [
                    [9, 4],
                    [9, 5],
                    [9, 6],
                    [9, 7]
                ],
                "EAST": [
                    [9, 8],
                    [9, 9],
                    [9, 10],
                    [9, 11]
                ],
                "SOUTH": [
                    [9, 12],
                    [9, 13],
                    [9, 14],
                    [9, 15]
                ],
                "WEST": [
                    [9, 16],
                    [9, 17],
                    [9, 18],
                    [9, 19]
                ]
            }
        },
        "7": {
            "default": [10, 0],
            "actions": {
                "STOP": [
                    [10, 0],
                    [10, 1],
                    [10, 2],
                    [10, 3]
                ],
                "NORTH": [
                    [10, 4],
                    [10, 5],
                    [10, 6],
                    [10, 7]
                ],
                "EAST": [
                    [10, 8],
                    [10, 9],
                    [10, 10],
                    [10, 11]
                ],
                "SOUTH": [
                    [10, 12],
                    [10, 13],
                    [10, 14],
                    [10, 15]
                ],
                "WEST": [
                    [10, 16],
                    [10, 17],
                    [10, 18],
                    [10, 19]
                ]
            }
        },
        "8": {
            "default": [11, 0],
            "actions": {
                "STOP": [
                    [11, 0],
                    [11, 1],
                    [11, 2],
                    [11, 3]
                ],
                "NORTH": [
                    [11, 4],
                    [11, 5],
                    [11, 6],
                    [11, 7]
                ],
                "EAST": [
                    [11, 8],
                    [11, 9],
                    [11, 10],
                    [11, 11]
                ],
                "SOUTH": [
                    [11, 12],
                    [11, 13],
                    [11, 14],
                    [11, 15]
                ],
                "WEST": [
                    [11, 16],
                    [11, 17],
                    [11, 18],
                    [11, 19]
                ]
            }
        },
        "9": {
            "default": [12, 0],
            "actions": {
                "STOP": [
                    [12, 0],
                    [12, 1],
                    [12, 2],
                    [12, 3]
                ],
                "NORTH": [
                    [12, 4],
                    [12, 5],
                    [12, 6],
                    [12, 7]
                ],
                "EAST": [
                    [12, 8],
                    [12, 9],
                    [12, 10],
                    [12, 11]
                ],
                "SOUTH": [
                    [12, 12],
                    [12, 13],
                    [12, 14],
                    [12, 15]
                ],
                "WEST": [
                    [12, 16],
                    [12, 17],
                    [12, 18],
                    [12, 19]
                ]
            }
        }
    }
}
